{
  "runner": "GitHub_Actions_1000000313",
  "timestamp": "2026-02-23T21:25:55Z",
  "total_failed": 743249,
  "total_healthy": 48760,
  "total_processed": 792013,
  "workers": [
    {
      "chunk_id": 0,
      "runner_name": "GitHub_Actions_1000000311",
      "status": "complete",
      "total_in_chunk": 198004,
      "processed": 198004,
      "ping_pass": 15703,
      "ping_fail": 182301,
      "speed_pass": 13878,
      "speed_fail": 1825,
      "healthy_output": 13878,
      "remaining": 0,
      "started_at": "2026-02-23T20:43:49Z",
      "finished_at": "2026-02-23T21:25:12Z",
      "duration_secs": 2483.183858952
    },
    {
      "chunk_id": 1,
      "runner_name": "GitHub_Actions_1000000309",
      "status": "complete",
      "total_in_chunk": 198003,
      "processed": 198003,
      "ping_pass": 13663,
      "ping_fail": 184340,
      "speed_pass": 12100,
      "speed_fail": 1563,
      "healthy_output": 12100,
      "remaining": 0,
      "started_at": "2026-02-23T20:43:51Z",
      "finished_at": "2026-02-23T21:23:51Z",
      "duration_secs": 2399.773896511
    },
    {
      "chunk_id": 2,
      "runner_name": "GitHub_Actions_1000000310",
      "status": "complete",
      "total_in_chunk": 198003,
      "processed": 198003,
      "ping_pass": 13437,
      "ping_fail": 184566,
      "speed_pass": 11919,
      "speed_fail": 1518,
      "healthy_output": 11919,
      "remaining": 0,
      "started_at": "2026-02-23T20:43:52Z",
      "finished_at": "2026-02-23T21:23:59Z",
      "duration_secs": 2406.915802413
    },
    {
      "chunk_id": 3,
      "runner_name": "GitHub_Actions_1000000312",
      "status": "complete",
      "total_in_chunk": 198003,
      "processed": 198003,
      "ping_pass": 12228,
      "ping_fail": 185775,
      "speed_pass": 10867,
      "speed_fail": 1361,
      "healthy_output": 10867,
      "remaining": 0,
      "started_at": "2026-02-23T20:43:51Z",
      "finished_at": "2026-02-23T21:21:59Z",
      "duration_secs": 2287.05811053
    }
  ]
}