{
  "runner": "GitHub_Actions_1000001791",
  "timestamp": "2026-03-20T08:39:52Z",
  "total_failed": 656752,
  "total_healthy": 30424,
  "total_processed": 687180,
  "workers": [
    {
      "chunk_id": 0,
      "runner_name": "GitHub_Actions_1000001790",
      "status": "complete",
      "total_in_chunk": 171795,
      "processed": 171795,
      "ping_pass": 9706,
      "ping_fail": 162089,
      "speed_pass": 8420,
      "speed_fail": 1286,
      "healthy_output": 8420,
      "remaining": 0,
      "started_at": "2026-03-20T08:03:29Z",
      "finished_at": "2026-03-20T08:38:13Z",
      "duration_secs": 2083.365370423
    },
    {
      "chunk_id": 1,
      "runner_name": "GitHub_Actions_1000001788",
      "status": "complete",
      "total_in_chunk": 171795,
      "processed": 171795,
      "ping_pass": 8391,
      "ping_fail": 163404,
      "speed_pass": 7318,
      "speed_fail": 1073,
      "healthy_output": 7318,
      "remaining": 0,
      "started_at": "2026-03-20T08:03:28Z",
      "finished_at": "2026-03-20T08:37:05Z",
      "duration_secs": 2016.492221072
    },
    {
      "chunk_id": 2,
      "runner_name": "GitHub_Actions_1000001787",
      "status": "complete",
      "total_in_chunk": 171795,
      "processed": 171795,
      "ping_pass": 7963,
      "ping_fail": 163832,
      "speed_pass": 6831,
      "speed_fail": 1132,
      "healthy_output": 6831,
      "remaining": 0,
      "started_at": "2026-03-20T08:03:29Z",
      "finished_at": "2026-03-20T08:38:50Z",
      "duration_secs": 2121.185347683
    },
    {
      "chunk_id": 3,
      "runner_name": "GitHub_Actions_1000001789",
      "status": "complete",
      "total_in_chunk": 171795,
      "processed": 171795,
      "ping_pass": 8975,
      "ping_fail": 162820,
      "speed_pass": 7859,
      "speed_fail": 1116,
      "healthy_output": 7859,
      "remaining": 0,
      "started_at": "2026-03-20T08:03:33Z",
      "finished_at": "2026-03-20T08:36:09Z",
      "duration_secs": 1956.066008354
    }
  ]
}