{
  "runner": "GitHub_Actions_1000001473",
  "timestamp": "2026-03-15T02:46:56Z",
  "total_failed": 664966,
  "total_healthy": 41109,
  "total_processed": 706082,
  "workers": [
    {
      "chunk_id": 0,
      "runner_name": "GitHub_Actions_1000001469",
      "status": "complete",
      "total_in_chunk": 176521,
      "processed": 176521,
      "ping_pass": 13430,
      "ping_fail": 163091,
      "speed_pass": 11546,
      "speed_fail": 1884,
      "healthy_output": 11546,
      "remaining": 0,
      "started_at": "2026-03-15T02:08:55Z",
      "finished_at": "2026-03-15T02:46:17Z",
      "duration_secs": 2242.541695411
    },
    {
      "chunk_id": 1,
      "runner_name": "GitHub_Actions_1000001471",
      "status": "complete",
      "total_in_chunk": 176521,
      "processed": 176521,
      "ping_pass": 11799,
      "ping_fail": 164722,
      "speed_pass": 10470,
      "speed_fail": 1329,
      "healthy_output": 10470,
      "remaining": 0,
      "started_at": "2026-03-15T02:08:46Z",
      "finished_at": "2026-03-15T02:45:48Z",
      "duration_secs": 2222.231319979
    },
    {
      "chunk_id": 2,
      "runner_name": "GitHub_Actions_1000001470",
      "status": "complete",
      "total_in_chunk": 176520,
      "processed": 176520,
      "ping_pass": 10555,
      "ping_fail": 165965,
      "speed_pass": 9341,
      "speed_fail": 1214,
      "healthy_output": 9341,
      "remaining": 0,
      "started_at": "2026-03-15T02:08:49Z",
      "finished_at": "2026-03-15T02:45:08Z",
      "duration_secs": 2179.19400515
    },
    {
      "chunk_id": 3,
      "runner_name": "GitHub_Actions_1000001472",
      "status": "complete",
      "total_in_chunk": 176520,
      "processed": 176520,
      "ping_pass": 11109,
      "ping_fail": 165411,
      "speed_pass": 9759,
      "speed_fail": 1350,
      "healthy_output": 9759,
      "remaining": 0,
      "started_at": "2026-03-15T02:08:45Z",
      "finished_at": "2026-03-15T02:43:27Z",
      "duration_secs": 2082.387290118
    }
  ]
}